django_tidyfields/__init__.py
django_tidyfields/apps.py
django_tidyfields/fields.py
django_tidyfields-1.2.3.dist-info/LICENSE
django_tidyfields-1.2.3.dist-info/METADATA
django_tidyfields-1.2.3.dist-info/WHEEL
django_tidyfields-1.2.3.dist-info/RECORD
