Metadata-Version: 2.1
Name: django_tidyfields
Version: 1.2.3
Summary: Easily accept html input with Django models, templates and DRF serializers.
Home-page: https://gitlab.com/routhio/python/django_tidyfields
License: MIT
Keywords: django,lxml,input,html,fields
Author: Chris Routh
Author-email: chris@routh.io
Requires-Python: >=3.9.0,<4.0
Classifier: Framework :: Django
Classifier: Framework :: Django :: 3.2
Classifier: Framework :: Django :: 4.0
Classifier: Framework :: Django :: 4.1
Classifier: Framework :: Django :: 4.2
Classifier: Intended Audience :: Developers
Classifier: License :: OSI Approved :: MIT License
Classifier: Programming Language :: Python :: 3
Classifier: Programming Language :: Python :: 3.9
Classifier: Programming Language :: Python :: 3.10
Classifier: Programming Language :: Python :: 3.11
Classifier: Programming Language :: Python :: 3.12
Classifier: Topic :: Software Development :: Libraries :: Python Modules
Provides-Extra: docs
Provides-Extra: pylint
Requires-Dist: Django (>=3.2)
Requires-Dist: lxml (==4.9.3)
Project-URL: Repository, https://gitlab.com/routhio/python/django_tidyfields
